mxm/dataio/__init__.py
mxm/dataio/_data/seeds/dataio/default.yaml
mxm/dataio/_data/seeds/dataio/environment.yaml
mxm/dataio/_data/seeds/dataio/local.yaml
mxm/dataio/_data/seeds/dataio/machine.yaml
mxm/dataio/_data/seeds/dataio/profile.yaml
mxm/dataio/adapters.py
mxm/dataio/api.py
mxm/dataio/cache.py
mxm/dataio/config/__init__.py
mxm/dataio/config/config.py
mxm/dataio/models.py
mxm/dataio/py.typed
mxm/dataio/registry.py
mxm/dataio/store.py
mxm_dataio-0.4.1.dist-info/METADATA
mxm_dataio-0.4.1.dist-info/WHEEL
mxm_dataio-0.4.1.dist-info/licenses/LICENSE
mxm_dataio-0.4.1.dist-info/RECORD
