Metadata-Version: 2.4
Name: mxm-dataio
Version: 0.4.1
Summary: **Unified ingestion, caching, and audit layer for Money Ex Machina.**
License: MIT
License-File: LICENSE
Author: mxm
Author-email: contact@moneyexmachina.com
Requires-Python: >=3.13,<3.15
Classifier: License :: OSI Approved :: MIT License
Classifier: Programming Language :: Python :: 3
Classifier: Programming Language :: Python :: 3.13
Classifier: Programming Language :: Python :: 3.14
Classifier: Typing :: Typed
Requires-Dist: mxm-config (>=0.5.0)
Requires-Dist: mxm-types (>=0.1.1,<0.2.0)
